dolead_entry_points/__init__.py
dolead_entry_points/client.py
dolead_entry_points/server.py
dolead_entry_points-0.0.13.dist-info/LICENSE
dolead_entry_points-0.0.13.dist-info/METADATA
dolead_entry_points-0.0.13.dist-info/WHEEL
dolead_entry_points-0.0.13.dist-info/RECORD
