Metadata-Version: 2.1
Name: dolead-entry-points
Version: 0.0.13
Summary: Multiple entry points generator
License: GPLv3
Author: François Schmidts
Author-email: francois@schmidts.fr
Requires-Python: >=3.9,<4.0
Classifier: License :: Other/Proprietary License
Classifier: Programming Language :: Python :: 3
Classifier: Programming Language :: Python :: 3.9
Classifier: Programming Language :: Python :: 3.10
Classifier: Programming Language :: Python :: 3.11
Classifier: Programming Language :: Python :: 3.12
Requires-Dist: celery (>=3.1.17,<6)
Requires-Dist: requests (>=2.13.0)
